coverpy/__init__.py
coverpy/coverpy.py
coverpy/exceptions.py
coverpy/__pycache__/__init__.cpython-35.pyc
coverpy/__pycache__/coverpy.cpython-35.pyc
coverpy/__pycache__/exceptions.cpython-35.pyc
coverpy-0.0.4.dist-info/DESCRIPTION.rst
coverpy-0.0.4.dist-info/METADATA
coverpy-0.0.4.dist-info/RECORD
coverpy-0.0.4.dist-info/WHEEL
coverpy-0.0.4.dist-info/metadata.json
coverpy-0.0.4.dist-info/top_level.txt
test/__init__.py
test/test_coverpy.py
test/__pycache__/__init__.cpython-35.pyc
test/__pycache__/test_coverpy.cpython-35.pyc
