Metadata-Version: 2.0
Name: coverpy
Version: 0.0.4
Summary: A wrapper for iTunes Search API
Home-page: UNKNOWN
Author: fallenshell
Author-email: dev@mxio.us
License: MIT License
Keywords: itunes search api wrapper simple clear cover album art music
Platform: UNKNOWN
Requires-Dist: requests
